pome7o/say.py
pome7o-0.2.0.dist-info/LICENSE
pome7o-0.2.0.dist-info/METADATA
pome7o-0.2.0.dist-info/WHEEL
pome7o-0.2.0.dist-info/RECORD
