Metadata-Version: 2.1
Name: pome7o
Version: 0.2.0
Summary: pome7o
Author: hanyu
Author-email: han_yu@hzlh.com
Requires-Python: >=3.10,<3.12
Classifier: License :: OSI Approved :: MIT License
Classifier: Operating System :: OS Independent
Classifier: Programming Language :: Python :: 3
Classifier: Programming Language :: Python :: 3.10
Classifier: Programming Language :: Python :: 3.11
